{"cameraMode":{"drawMode":0,"name":"Shaded","section":"Shading Mode"},"sceneLighting":true,"audioPlay":false,"sceneViewState":{"showFog":true,"showMaterialUpdate":false,"showSkybox":true,"showFlares":true,"showImageEffects":true,"showParticleSystems":true},"in2DMode":false,"pivot":{"x":234.3987579345703,"y":22.52695083618164,"z":-329.8617248535156},"rotation":{"x":-0.26081857085227969,"y":0.2821066975593567,"z":-0.07999756932258606,"w":-0.9197929501533508},"size":436.9318542480469,"orthographic":false}